README.md
comma/__init__.py
comma/abstract.py
comma/classes/__init__.py
comma/classes/file.py
comma/classes/row.py
comma/classes/slices.py
comma/classes/table.py
comma/config.py
comma/exceptions.py
comma/extras.py
comma/helpers.py
comma/methods.py
comma/typing.py
comma-0.5.3.dist-info/LICENSE
comma-0.5.3.dist-info/WHEEL
comma-0.5.3.dist-info/METADATA
comma-0.5.3.dist-info/RECORD
