Metadata-Version: 2.1
Name: comma
Version: 0.5.3
Summary: Python CSV, and delimiter-spaced files, for humans!
Home-page: https://github.com/jlumbroso/comma
License: LGPL-3.0-or-later
Keywords: CSV,CSV library,CSV reading,DSV library,CSV manipulation
Author: Jérémie Lumbroso
Author-email: lumbroso@cs.princeton.edu
Requires-Python: >=3.6,<4.0
Classifier: Development Status :: 4 - Beta
Classifier: License :: OSI Approved :: GNU Lesser General Public License v3 or later (LGPLv3+)
Classifier: Programming Language :: Python :: 3
Classifier: Programming Language :: Python :: 3.6
Classifier: Programming Language :: Python :: 3.7
Classifier: Programming Language :: Python :: 3.8
Classifier: Programming Language :: Python :: 3.9
Classifier: Topic :: Scientific/Engineering :: Information Analysis
Classifier: Topic :: Software Development :: Libraries :: Python Modules
Classifier: Topic :: Text Processing
Classifier: Topic :: Text Processing :: General
Provides-Extra: autodetect
Provides-Extra: net
Requires-Dist: binaryornot (>=0.4.4,<0.5.0); extra == "autodetect"
Requires-Dist: chardet (>=3.0.4,<4.0.0); extra == "autodetect"
Requires-Dist: clevercsv (>=0.6.3,<0.7.0); (python_version >= "3.6" and python_version < "4.0") and (extra == "autodetect")
Requires-Dist: requests (>=2.23.0,<3.0.0); extra == "net"
Project-URL: Repository, https://github.com/jlumbroso/comma
